[
  {
    "nombre": "Club Otorongo",
    "descripcion": "Antecedentes de todos los candidatos",
    "autor": "La Encerrona y AniversarioPerú",
    "url": "https://otorongo.club/",
    "categoria": "Antecedentes",
    "destacado": true,
    "imagen": "img/logoprueba.jpeg"
  },
  {
    "nombre": "Compara Encuestas",
    "descripcion": "Ipsos, Datum, IEP y CPI en un solo sitio",
    "autor": "La Encerrona",
    "url": "https://laencerrona.pe/2026/02/10/encuestas/",
    "categoria": "Encuestas",
    "destacado": true,
    "imagen": "img/compara-encuestas.png"
  },
  {
    "nombre": "El mal menor",
    "descripcion": "Descubre a tu candidato ideal",
    "autor": "José Burga y otros",
    "url": "https://elmalmenor.com/",
    "categoria": "Plan de gobierno",
    "destacado": false,
    "imagen": "img/logoprueba.jpeg"
  },
  {
    "nombre": "Hechos y no palabras",
    "descripcion": "Votaciones de congresistas",
    "autor": "GIES PUCP",
    "url": "https://hechosynopalabras.pe/",
    "categoria": "Antecedentes",
    "destacado": false,
    "imagen": "img/hechos-palabras.png"
  },
  {
    "nombre": "Capibarismo",
    "descripcion": "Simulador de elecciones",
    "autor": "Sin identificar",
    "url": "https://capibarismo.com/",
    "categoria": "Simulador",
    "destacado": false,
    "imagen": "img/capibarismo.png"
  },
  {
    "nombre": "Chapa tu candidato",
    "descripcion": "IA analiza planes de gobierno",
    "autor": "Sin identificar",
    "url": "https://chapatucandidato.com/",
    "categoria": "Plan de gobierno",
    "destacado": false,
    "imagen": "img/chapa-candidato.png"
  },
  {
    "nombre": "Decide tu voto",
    "descripcion": "Test de afinidad con candidatos",
    "autor": "Miguel Angel Tello Silva",
    "url": "https://www.tuvotoperu.com/",
    "categoria": "Plan de gobierno",
    "destacado": false,
    "imagen": "img/decide-voto.png"
  },
  {
    "nombre": "Votar es clave",
    "descripcion": "Info general para jóvenes",
    "autor": "PUCP",
    "url": "https://votaresclave.pucp.edu.pe/",
    "categoria": "Otros",
    "destacado": false,
    "imagen": "img/votar-clave.png"
  },
  {
    "nombre": "Revisa tu candidato",
    "descripcion": "Trayectoria, sentencias y más",
    "autor": "Transparencia y otros",
    "url": "https://revisatucandidato.pe/",
    "categoria": "Antecedentes",
    "destacado": false,
    "imagen": "img/revisa-candidato.jpg"
  },
  {
    "nombre": "Planómetro 2026",
    "descripcion": "Visualiza los planes de gobierno",
    "autor": "Noam López",
    "url": "https://noamlv.github.io/PlanesPeru26/",
    "categoria": "Plan de gobierno",
    "destacado": false,
    "imagen": "img/planometro.png"
  },
  {
    "nombre": "Checa bien",
    "descripcion": "Propuestas, trayectoria e investigaciones",
    "autor": "W. Benavente, J. Piere, Romaid",
    "url": "https://www.checabien.com/",
    "categoria": "Antecedentes",
    "destacado": false,
    "imagen": "img/checa-bien.jpg"
  }
]
